[
    {
        "user": "U08MP3Z41T3",
        "type": "message",
        "ts": "1747212561.706709",
        "client_msg_id": "695a6155-d5b1-4066-b8a8-ce3c84ae20e6",
        "text": "2025년 5월 14일 (수)\n`&lt; 스크럼 내용 &gt;`\n```1. 업무 일정 기한에 따른 관리\n2. 모바일 기획\/설계 및 요구사항 정의 15일 부터 시작```\n`&lt; 총괄 &gt;`\n```[김정중]\n완료\nㄴ 대시보드, 퀵메뉴 UX\/UI 정의\nㄴ 형상관리 웹서비스팀 조직 분리 이관작업\n\n진행\nㄴ 일정관리\nㄴ (FE) SSO 개발기 작업\nㄴ DMZ 일진제강 모바일 프로젝트 이관 작업\n\t- 방화벽 오픈 요청\n\t- MOBILE 프론트 자동 배포 환경 작업(Runner)\n\t- CI\/CD 작성\nㄴ 모바일) 기획\/설계 및 요구사항\n\t- 대시보드, 퀵메뉴\n\t- 문서(전표) 작성, 조회\n\t- 더보기\nㄴ 개발기 서버 세팅\n\t- MQTT 서비스 선정```\n`&lt; 백엔드 &gt;`\n```[박광호]\n완료\nㄴ 개발서버 SSO 로그인 동작 확인\nㄴ JWT cookie 저장(개선)\n진행\nㄴ 전자결재 재기안 프로세스 테스트\n[박수환]\n완료\nㄴ 겸직 비활성화, 삭제 문제에 관한 논의\n진행\nㄴ 사용자 CRUD - 겸직 관련 추가 변경사항 개발\nㄴ employee 테이블 사용여부 추가\n[권연주]\n완료\nㄴ 로그인\n - 비밀번호 찾기 인증번호 확인 api\n진행\nㄴ 사용자관리\n - 사용자 엑셀업로드 수정```\n`&lt; 프론트엔드 &gt;`\n```[우태림]\n완료\nㄴ Dashboard Quick Menu UI\n진행\nㄴ 대시보드 재구성\nㄴ 메뉴 대시보드 아이콘 업로드 기능 추가\n\n[김보민]\n진행\nㄴ 시스템설정 &gt; 사용자등록\n - 사용자등록(겸직) UI 추가\n - 상단 Navigator 겸직 변경 UI 추가 및 스토어 갱신\nㄴ 시스템설정 &gt; 권한관리\n - 부서, 직책 UI 필드 추가\nㄴ 시스템설정 &gt; 직위관리\n - 임직원 테이블 UI 대표사용자만 표기\nㄴ 시스템설정 &gt; 부서관리\n - 임직원 테이블 UI 표기 개선\nㄴ 시스템설정 &gt; 직책관리\n - 임직원 테이블 UI 표기 개선\nㄴ 로그인 &gt; 비밀번호 찾기\n\n[전원재]\n완료\nㄴ 전자결재 &gt; 지출결의서\n - 전표 UI 모달 추가(추가, 삭제, 복사)\n진행\nㄴ 전자결재 &gt; 지출결의서\n - 전표 UI 모달 추가(분할)```\n`&lt; 모바일 &gt;`\n```[홍제원]\n완료\nㄴ 인트로 화면 제작\n\t- AOS] install referrer api 연동 및 라우팅\n\n진행\nㄴ 딥링크 제작\n\t- 딥링크 흐름 정의 및 링크 설계\nㄴ 그룹웨어\n\t- 그룹웨어 앱 내재화를 위한 정보 공유 ( 요청자 : 고민정 팀장 , 수신자 : 길준성 차장)```\n`&lt; 디자인 &gt;`\n```[차윤수]\n완료\nㄴ 사용자관리 : 겸직\n\t- 엑셀일괄등록 겸직여부 고려한 양식변경\n진행\nㄴ 로그인 &gt; 비밀번호 찾기 기능\n\t- PC: 로그인화면 &gt; 비밀번호찾기 프로세스 화면추가\n\t- 이메일: 비밀번호초기와 인증코드 이메일 화면 기획\n\t- Mobile : 아이디 찾기 추가 및 UI개선\n\nㄴ 브랜드사이트 - 출입방문관리솔루션(SynFlo Visit\n\t- 소개 페이지 디자인작업\n\t- 솔루션 기능별 이미지 가공 작업\n\t- 2.0 대시보드 화면 기획\/디자인\n\t\t- 재무담당자용 가로4단 레이아웃으로 변경\n\t\t- 컨텐츠 재구성 회의\n\t\t- 퀵메뉴 디자인 변경```\n",
        "team": "T06BW9BS3L6",
        "user_team": "T06BW9BS3L6",
        "source_team": "T06BW9BS3L6",
        "user_profile": {
            "avatar_hash": "gfe6fa4b5458",
            "image_72": "https:\/\/secure.gravatar.com\/avatar\/fe6fa4b5458612c8bfd45db233b5166d.jpg?s=72&d=https%3A%2F%2Fa.slack-edge.com%2Fdf10d%2Fimg%2Favatars%2Fava_0005-72.png",
            "first_name": "JayKim",
            "real_name": "JayKim",
            "display_name": "JayKim",
            "team": "T06BW9BS3L6",
            "name": "jayx",
            "is_restricted": false,
            "is_ultra_restricted": false
        },
        "blocks": [
            {
                "type": "rich_text",
                "block_id": "jIlBe",
                "elements": [
                    {
                        "type": "rich_text_section",
                        "elements": [
                            {
                                "type": "text",
                                "text": "2025년 5월 14일 (수)\n"
                            },
                            {
                                "type": "text",
                                "text": "< 스크럼 내용 >",
                                "style": {
                                    "code": true
                                }
                            },
                            {
                                "type": "text",
                                "text": "\n"
                            }
                        ]
                    },
                    {
                        "type": "rich_text_preformatted",
                        "elements": [
                            {
                                "type": "text",
                                "text": "1. 업무 일정 기한에 따른 관리\n2. 모바일 기획\/설계 및 요구사항 정의 15일 부터 시작"
                            }
                        ],
                        "border": 0
                    },
                    {
                        "type": "rich_text_section",
                        "elements": [
                            {
                                "type": "text",
                                "text": "< 총괄 >",
                                "style": {
                                    "code": true
                                }
                            },
                            {
                                "type": "text",
                                "text": "\n"
                            }
                        ]
                    },
                    {
                        "type": "rich_text_preformatted",
                        "elements": [
                            {
                                "type": "text",
                                "text": "[김정중]\n완료\nㄴ 대시보드, 퀵메뉴 UX\/UI 정의\nㄴ 형상관리 웹서비스팀 조직 분리 이관작업\n\n진행\nㄴ 일정관리\nㄴ (FE) SSO 개발기 작업\nㄴ DMZ 일진제강 모바일 프로젝트 이관 작업\n\t- 방화벽 오픈 요청\n\t- MOBILE 프론트 자동 배포 환경 작업(Runner)\n\t- CI\/CD 작성\nㄴ 모바일) 기획\/설계 및 요구사항\n\t- 대시보드, 퀵메뉴\n\t- 문서(전표) 작성, 조회\n\t- 더보기\nㄴ 개발기 서버 세팅\n\t- MQTT 서비스 선정"
                            }
                        ],
                        "border": 0
                    },
                    {
                        "type": "rich_text_section",
                        "elements": [
                            {
                                "type": "text",
                                "text": "< 백엔드 >",
                                "style": {
                                    "code": true
                                }
                            },
                            {
                                "type": "text",
                                "text": "\n"
                            }
                        ]
                    },
                    {
                        "type": "rich_text_preformatted",
                        "elements": [
                            {
                                "type": "text",
                                "text": "[박광호]\n완료\nㄴ 개발서버 SSO 로그인 동작 확인\nㄴ JWT cookie 저장(개선)\n진행\nㄴ 전자결재 재기안 프로세스 테스트\n[박수환]\n완료\nㄴ 겸직 비활성화, 삭제 문제에 관한 논의\n진행\nㄴ 사용자 CRUD - 겸직 관련 추가 변경사항 개발\nㄴ employee 테이블 사용여부 추가\n[권연주]\n완료\nㄴ 로그인\n - 비밀번호 찾기 인증번호 확인 api\n진행\nㄴ 사용자관리\n - 사용자 엑셀업로드 수정"
                            }
                        ],
                        "border": 0
                    },
                    {
                        "type": "rich_text_section",
                        "elements": [
                            {
                                "type": "text",
                                "text": "< 프론트엔드 >",
                                "style": {
                                    "code": true
                                }
                            },
                            {
                                "type": "text",
                                "text": "\n"
                            }
                        ]
                    },
                    {
                        "type": "rich_text_preformatted",
                        "elements": [
                            {
                                "type": "text",
                                "text": "[우태림]\n완료\nㄴ Dashboard Quick Menu UI\n진행\nㄴ 대시보드 재구성\nㄴ 메뉴 대시보드 아이콘 업로드 기능 추가\n\n[김보민]\n진행\nㄴ 시스템설정 > 사용자등록\n - 사용자등록(겸직) UI 추가\n - 상단 Navigator 겸직 변경 UI 추가 및 스토어 갱신\nㄴ 시스템설정 > 권한관리\n - 부서, 직책 UI 필드 추가\nㄴ 시스템설정 > 직위관리\n - 임직원 테이블 UI 대표사용자만 표기\nㄴ 시스템설정 > 부서관리\n - 임직원 테이블 UI 표기 개선\nㄴ 시스템설정 > 직책관리\n - 임직원 테이블 UI 표기 개선\nㄴ 로그인 > 비밀번호 찾기\n\n[전원재]\n완료\nㄴ 전자결재 > 지출결의서\n - 전표 UI 모달 추가(추가, 삭제, 복사)\n진행\nㄴ 전자결재 > 지출결의서\n - 전표 UI 모달 추가(분할)"
                            }
                        ],
                        "border": 0
                    },
                    {
                        "type": "rich_text_section",
                        "elements": [
                            {
                                "type": "text",
                                "text": "< 모바일 >",
                                "style": {
                                    "code": true
                                }
                            },
                            {
                                "type": "text",
                                "text": "\n"
                            }
                        ]
                    },
                    {
                        "type": "rich_text_preformatted",
                        "elements": [
                            {
                                "type": "text",
                                "text": "[홍제원]\n완료\nㄴ 인트로 화면 제작\n\t- AOS] install referrer api 연동 및 라우팅\n\n진행\nㄴ 딥링크 제작\n\t- 딥링크 흐름 정의 및 링크 설계\nㄴ 그룹웨어\n\t- 그룹웨어 앱 내재화를 위한 정보 공유 ( 요청자 : 고민정 팀장 , 수신자 : 길준성 차장)"
                            }
                        ],
                        "border": 0
                    },
                    {
                        "type": "rich_text_section",
                        "elements": [
                            {
                                "type": "text",
                                "text": "< 디자인 >",
                                "style": {
                                    "code": true
                                }
                            },
                            {
                                "type": "text",
                                "text": "\n"
                            }
                        ]
                    },
                    {
                        "type": "rich_text_preformatted",
                        "elements": [
                            {
                                "type": "text",
                                "text": "[차윤수]\n완료\nㄴ 사용자관리 : 겸직\n\t- 엑셀일괄등록 겸직여부 고려한 양식변경\n진행\nㄴ 로그인 > 비밀번호 찾기 기능\n\t- PC: 로그인화면 > 비밀번호찾기 프로세스 화면추가\n\t- 이메일: 비밀번호초기와 인증코드 이메일 화면 기획\n\t- Mobile : 아이디 찾기 추가 및 UI개선\n\nㄴ 브랜드사이트 - 출입방문관리솔루션(SynFlo Visit\n\t- 소개 페이지 디자인작업\n\t- 솔루션 기능별 이미지 가공 작업\n\t- 2.0 대시보드 화면 기획\/디자인\n\t\t- 재무담당자용 가로4단 레이아웃으로 변경\n\t\t- 컨텐츠 재구성 회의\n\t\t- 퀵메뉴 디자인 변경"
                            }
                        ],
                        "border": 0
                    },
                    {
                        "type": "rich_text_section",
                        "elements": []
                    }
                ]
            }
        ]
    }
]